async_storages/__init__.py
async_storages/backends/__init__.py
async_storages/backends/base.py
async_storages/backends/fs.py
async_storages/backends/memory.py
async_storages/backends/s3.py
async_storages/contrib/__init__.py
async_storages/contrib/starlette.py
async_storages/file_storage.py
async_storages/helpers.py
async_storages/py.typed
async_storages-0.7.0.dist-info/LICENSE
async_storages-0.7.0.dist-info/METADATA
async_storages-0.7.0.dist-info/WHEEL
async_storages-0.7.0.dist-info/RECORD
