Metadata-Version: 2.1
Name: async_storages
Version: 0.7.0
Summary: Simple filesytem abstraction for async Python
Home-page: https://github.com/alex-oleshkevich/async_storages
License: MIT
Author: Alex Oleshkevich
Author-email: alex.oleshkevich@gmail.com
Requires-Python: >=3.10,<4.0
Classifier: Development Status :: 5 - Production/Stable
Classifier: Environment :: Web Environment
Classifier: Intended Audience :: Developers
Classifier: License :: OSI Approved :: MIT License
Classifier: Operating System :: OS Independent
Classifier: Programming Language :: Python :: 3
Classifier: Programming Language :: Python :: 3.10
Classifier: Programming Language :: Python :: 3.11
Classifier: Programming Language :: Python :: 3.12
Classifier: Programming Language :: Python :: 3.13
Classifier: Topic :: Software Development :: Libraries :: Python Modules
Classifier: Typing :: Typed
Provides-Extra: s3
Requires-Dist: aioboto3 (>=13,<14) ; extra == "s3"
Requires-Dist: anyio (>=4,<5)
Requires-Dist: sanitize-filename (>=1.2.0,<2.0.0)
Project-URL: Documentation, https://github.com/alex-oleshkevich/async_storages
Project-URL: Repository, https://github.com/alex-oleshkevich/async_storages
